mcp_server/__init__.py
mcp_server/mcp_server.py
mcp_server/mcp_server_fastmcp.py
mcp_server/server.py
mcp_server/server_fastmcp_new.py
mcp_server/server_simple.py
mcp_server/assets/commit_template.default.txt
mcp_server/cli/main.py
mcp_server/git_backend/commits.py
mcp_server/git_backend/history.py
mcp_server/git_backend/repo.py
mcp_server/git_backend/safety.py
mcp_server/git_backend/staging.py
mcp_server/git_backend/templates.py
mcp_server/tools/git_fs.py
mcp_server/tools/integrate_code_diff.py
mcp_server/tools/integrate_file_system.py
mcp_server/tools/integrate_text_replace.py
mcp_server/tools/reader.py
fs_git_mcp-0.1.0.dist-info/METADATA
fs_git_mcp-0.1.0.dist-info/WHEEL
fs_git_mcp-0.1.0.dist-info/entry_points.txt
fs_git_mcp-0.1.0.dist-info/licenses/LICENSE
fs_git_mcp-0.1.0.dist-info/RECORD
