Metadata-Version: 2.4
Name: fs-git-mcp
Version: 0.1.0
Summary: MCP Git-enforced filesystem with direct and staged modes
Project-URL: Homepage, https://github.com/wojons/fs-git-mcp
Project-URL: Repository, https://github.com/wojons/fs-git-mcp
Author-email: Alexis Okuwa <wojonstech@gmail.com>
Maintainer-email: Alexis Okuwa <wojonstech@gmail.com>
License: MIT
License-File: LICENSE
Keywords: ai,automation,filesystem,git,mcp,model-context-protocol
Classifier: Development Status :: 4 - Beta
Classifier: Intended Audience :: Developers
Classifier: License :: OSI Approved :: MIT License
Classifier: Operating System :: OS Independent
Classifier: Programming Language :: Python :: 3
Classifier: Programming Language :: Python :: 3.11
Classifier: Programming Language :: Python :: 3.12
Classifier: Programming Language :: Python :: 3.13
Classifier: Topic :: Software Development :: Libraries :: Python Modules
Classifier: Topic :: Software Development :: Version Control :: Git
Classifier: Topic :: System :: Filesystems
Requires-Python: >=3.11
Requires-Dist: dulwich>=0.21
Requires-Dist: gitpython>=3.1
Requires-Dist: mcp>=1.0.0
Requires-Dist: mcp[cli]
Requires-Dist: pydantic>=2.0
Requires-Dist: rich>=13.0
Requires-Dist: typer>=0.9
Provides-Extra: dev
Requires-Dist: black>=23.0; extra == 'dev'
Requires-Dist: hypothesis>=6.0; extra == 'dev'
Requires-Dist: mypy>=1.0; extra == 'dev'
Requires-Dist: pre-commit>=3.0; extra == 'dev'
Requires-Dist: pytest-asyncio>=0.21; extra == 'dev'
Requires-Dist: pytest>=7.0; extra == 'dev'
Requires-Dist: ruff>=0.1; extra == 'dev'
